walrusmemory/__init__.py
walrusmemory/main.py
walrusmemory-0.1.0.dist-info/METADATA
walrusmemory-0.1.0.dist-info/WHEEL
walrusmemory-0.1.0.dist-info/top_level.txt
walrusmemory-0.1.0.dist-info/RECORD
