Metadata-Version: 2.4
Name: walrusmemory
Version: 0.1.0
Summary: Walrus Memory
Author-email: Rishabh <prajapatirishabh04@gmail.com>
License: MIT
Requires-Python: >=3.12
